pyffmpeg/__init__.py
pyffmpeg/extract_functions.py
pyffmpeg/misc.py
pyffmpeg/pseudo_ffprobe.py
pyffmpeg/static/__init__.py
pyffmpeg/static/bin/__init__.py
pyffmpeg/static/bin/darwin/__init__.py
pyffmpeg/static/bin/linuxmod/__init__.py
pyffmpeg/static/bin/win32/__init__.py
pyffmpeg/static/bin/win32/win32.py
pyffmpeg-2.5.2.3.1.dist-info/licenses/LICENSE
pyffmpeg-2.5.2.3.1.dist-info/METADATA
pyffmpeg-2.5.2.3.1.dist-info/WHEEL
pyffmpeg-2.5.2.3.1.dist-info/top_level.txt
pyffmpeg-2.5.2.3.1.dist-info/RECORD
