Metadata-Version: 2.4
Name: pyffmpeg
Version: 2.5.2.3.1
Summary: FFmpeg wrapper for python
Home-page: https://github.com/deuteronomy-works/pyffmpeg
Author: Amoh - Gyebi Godwin Ampofo Michael
Author-email: amohgyebigodwin@gmail.com
Keywords: ffmpeg,FFmpeg,ffprobe,FFprobe,album art,cover art,metadata,conversion,converting,audio,video
Classifier: Programming Language :: Python
Classifier: Programming Language :: Python :: 3
Classifier: Development Status :: 5 - Production/Stable
Classifier: Intended Audience :: Developers
Classifier: License :: OSI Approved :: Apache Software License
Classifier: Operating System :: OS Independent
Classifier: Topic :: Software Development :: Libraries :: Python Modules
License-File: LICENSE
Dynamic: author
Dynamic: author-email
Dynamic: classifier
Dynamic: description
Dynamic: description-content-type
Dynamic: home-page
Dynamic: keywords
Dynamic: license-file
Dynamic: summary
